<!--
WARNING: THIS IS AN AUTO-GENERATED FILE. CHANGES TO IT ARE LIKELY TO BE
OVERWRITTEN AND LOST. Changes to this xml configuration should be made using:
  virsh nwfilter-edit no-mac-spoofing
or other application using the libvirt API.
-->

<filter name='no-mac-spoofing' chain='mac' priority='-800'>
  <uuid>2e1a97ee-9d8f-48a6-9fdc-a1b2d61dac6d</uuid>
  <rule action='return' direction='out' priority='500'>
    <mac srcmacaddr='$MAC'/>
  </rule>
  <rule action='drop' direction='out' priority='500'>
    <mac/>
  </rule>
</filter>
